neno/__init__.py
neno/__main__.py
neno/app.py
neno/client.py
neno/config.py
neno/config.yaml
neno/config_backends.py
neno/models.py
neno/requirements.txt
neno/runner.py
neno/server.py
neno/storage_backends.py
neno/util.py
neno/example-endpoint/manifest.json
neno/example-endpoint/template.txt
neno/example-endpoint/test-notebook.ipynb
neno-0.2.1.dist-info/METADATA
neno-0.2.1.dist-info/WHEEL
neno-0.2.1.dist-info/licenses/LICENSE
neno-0.2.1.dist-info/RECORD
